[
  {
    "id": "mag_subculjapan2012",
    "copy-from": "mag_animecon",
    "type": "BOOK",
    "name": "书籍(学习/双年展/日本亚文化 2012)",
    "description": "两年一度的杂志，专注于日本亚文化。 动漫、漫画、cosplay、模型、铁道等各种类型都用照片仔细讲解。 如果想要做好准备，将能够熟悉大致的趋势。"
  },
  {
    "id": "mag_subculjapan2014",
    "copy-from": "mag_animecon",
    "type": "BOOK",
    "name": "书籍(学习/双年展/日本亚文化 2014)",
    "description": "两年一度的杂志，专注于日本亚文化。 动漫、漫画、cosplay、模型、铁道等各种类型都用照片仔细讲解。 如果想要做好准备，将能够熟悉大致的趋势。"
  },
  {
    "id": "mag_subculjapan2016",
    "copy-from": "mag_animecon",
    "type": "BOOK",
    "name": "书籍(学习/双年展/日本亚文化 2016)",
    "description": "两年一度的杂志，专注于日本亚文化。 动漫、漫画、cosplay、模型、铁道等各种类型都用照片仔细讲解。 如果想要做好准备，将能够熟悉大致的趋势。"
  },
  {
    "id": "mag_subculjapan2018",
    "copy-from": "mag_animecon",
    "type": "BOOK",
    "name": "书籍(学习/双年展/日本亚文化 2018)",
    "description": "两年一度的杂志，专注于日本亚文化。 动漫、漫画、cosplay、模型、铁道等各种类型都用照片仔细讲解。 如果想要做好准备，将能够熟悉大致的趋势。"
  },
  {
    "id": "mag_subculjapan2020",
    "copy-from": "mag_animecon",
    "type": "BOOK",
    "name": "书籍(学习/双年展/日本亚文化 2020)",
    "description": "两年一度的杂志，专注于日本亚文化。 动漫、漫画、cosplay、模型、铁道等各种类型都用照片仔细讲解。 如果想要做好准备，将能够熟悉大致的趋势。"
  },
  {
    "id": "mag_subculjapan2021",
    "copy-from": "mag_animecon",
    "type": "BOOK",
    "name": "书籍(学习/双年展/日本亚文化 2022)",
    "description": "两年一度的杂志，专注于日本亚文化。 动漫、漫画、cosplay、模型、铁道等各种类型都用照片仔细讲解。 如果想要做好准备，将能够熟悉大致的趋势。"
  },
  {
    "id": "mag_subculjapan2022",
    "copy-from": "mag_animecon",
    "type": "BOOK",
    "name": "书籍(学习/双年展/日本亚文化 2012)",
    "description": "两年一度的杂志，专注于日本亚文化。 动漫、漫画、cosplay、模型、铁道等各种类型都用照片仔细讲解。 如果想要做好准备，将能够熟悉大致的趋势。"
  },
  {
    "//1": "バーチャルYouTuberとかも載っているのかもね！　説明文のバーチャルアイドルはマクロスプラスのシャロン・アップル。",
    "//2": "初のVOCALOIDがLEONとLOLA。日本初のVOCALOIDがMEIKO。実質的な意味での初めてのバーチャルアイドルが初音ミク。",
    "id": "mag_virtualsinger",
    "copy-from": "mag_animecon",
    "type": "BOOK",
    "name": "书籍(学习/虚拟歌手)",
    "description": "世界中のバーチャルシンガーを特集した雑誌です。90年代の日本のOVAに出てくるバーチャルアイドルに始まり、非常にマニアックな内容に触れた一冊です。"
  }
]